tree_sitter_ocaml-0.24.2.dist-info/RECORD
tree_sitter_ocaml-0.24.2.dist-info/WHEEL
tree_sitter_ocaml-0.24.2.dist-info/top_level.txt
tree_sitter_ocaml-0.24.2.dist-info/METADATA
tree_sitter_ocaml-0.24.2.dist-info/licenses/LICENSE
tree_sitter_ocaml/__init__.pyi
tree_sitter_ocaml/binding.c
tree_sitter_ocaml/__init__.py
tree_sitter_ocaml/py.typed
tree_sitter_ocaml/_binding.abi3.so
tree_sitter_ocaml/queries/tags.scm
tree_sitter_ocaml/queries/locals.scm
tree_sitter_ocaml/queries/highlights.scm
